eduvpn_common/__init__.py
eduvpn_common/event.py
eduvpn_common/loader.py
eduvpn_common/main.py
eduvpn_common/py.typed
eduvpn_common/state.py
eduvpn_common/types.py
eduvpn_common/lib/libeduvpn_common-4.0.0.so
eduvpn_common-4.0.0.dist-info/METADATA
eduvpn_common-4.0.0.dist-info/WHEEL
eduvpn_common-4.0.0.dist-info/top_level.txt
eduvpn_common-4.0.0.dist-info/RECORD
