Metadata-Version: 2.1
Name: eduvpn-common
Version: 4.0.0
Summary: Python wrapper for eduvpn-common, a codebase to build eduVPN clients with
Home-page: https://codeberg.org/eduVPN/eduvpn-common
Author: Jeroen Wijenbergh
Author-email: jeroen.wijenbergh@geant.org
License: MIT
Platform: UNKNOWN
Provides-Extra: lint
Requires-Dist: ruff ; extra == 'lint'
Provides-Extra: mypy
Requires-Dist: mypy ; extra == 'mypy'
